trand/__init__.py
trand/bedtools.py
trand/calculate_complexity.py
trand/consolidation.py
trand/event_analysis.py
trand/io.py
trand/main.py
trand/minimum_distance.py
trand/plot_events.py
trand/plot_functions.py
trand/plot_one_gtf_gene.py
trand/plot_one_gtf_pairwise.py
trand/plot_transcriptome.py
trand/plot_two_gtf_pairwise.py
trand/transcript_distance.py
trand-23.5.30.dist-info/LICENSE
trand-23.5.30.dist-info/METADATA
trand-23.5.30.dist-info/WHEEL
trand-23.5.30.dist-info/entry_points.txt
trand-23.5.30.dist-info/top_level.txt
trand-23.5.30.dist-info/RECORD
