Metadata-Version: 2.1
Name: trand
Version: 23.5.30
Summary: 'Transcript Distances'
Home-page: https://github.com/McIntyre-Lab/TranD
Author: McIntyre Lab, Universify of Florida
Author-email: om@rc.ufl.edu
License: MIT
Keywords: transcript event and distance analysis
Platform: any
Classifier: Development Status :: 4 - Beta
Classifier: Environment :: Console
Classifier: Intended Audience :: Science/Research
Classifier: Operating System :: OS Independent
Classifier: License :: OSI Approved :: MIT License
Classifier: Programming Language :: Python :: 3
Classifier: Topic :: Scientific/Engineering
Classifier: Topic :: Scientific/Engineering :: Bio-Informatics
Requires-Python: >=3.7
Requires-Dist: numpy (>=1.18)
Requires-Dist: pandas (>=1.2.4)
Requires-Dist: pybedtools (>=0.8)
Requires-Dist: pysam
Requires-Dist: matplotlib
Requires-Dist: seaborn (>=0.9.0)
Requires-Dist: loguru
Requires-Dist: upsetplot (>=0.4.1)
